setup.py
probability_distributions_drew/Binomialdistribution.py
probability_distributions_drew/Gaussiandistribution.py
probability_distributions_drew/Generaldistribution.py
probability_distributions_drew/__init__.py
probability_distributions_drew.egg-info/PKG-INFO
probability_distributions_drew.egg-info/SOURCES.txt
probability_distributions_drew.egg-info/dependency_links.txt
probability_distributions_drew.egg-info/not-zip-safe
probability_distributions_drew.egg-info/top_level.txt