Metadata-Version: 1.0
Name: probability-distributions-drew
Version: 0.2
Summary: Gaussian and Binomial distributions
Home-page: UNKNOWN
Author: Andrew Sithole
Author-email: andrewsithole7@gmail.com
License: UNKNOWN
Platform: UNKNOWN
